aider/__init__.py
aider/__main__.py
aider/analytics.py
aider/args.py
aider/args_formatter.py
aider/commands.py
aider/copypaste.py
aider/deprecated.py
aider/diffs.py
aider/dump.py
aider/editor.py
aider/exceptions.py
aider/format_settings.py
aider/gui.py
aider/help.py
aider/help_pats.py
aider/history.py
aider/io.py
aider/linter.py
aider/llm.py
aider/main.py
aider/mdstream.py
aider/models.py
aider/prompts.py
aider/reasoning_tags.py
aider/repo.py
aider/repomap.py
aider/report.py
aider/run_cmd.py
aider/scrape.py
aider/sendchat.py
aider/special.py
aider/urls.py
aider/utils.py
aider/versioncheck.py
aider/voice.py
aider/watch.py
aider/watch_prompts.py
aider/cli/__init__.py
aider/cli/operator.py
aider/coders/__init__.py
aider/coders/architect_coder.py
aider/coders/architect_prompts.py
aider/coders/ask_coder.py
aider/coders/ask_prompts.py
aider/coders/base_coder.py
aider/coders/base_prompts.py
aider/coders/chat_chunks.py
aider/coders/context_coder.py
aider/coders/context_prompts.py
aider/coders/editblock_coder.py
aider/coders/editblock_fenced_coder.py
aider/coders/editblock_fenced_prompts.py
aider/coders/editblock_func_coder.py
aider/coders/editblock_func_prompts.py
aider/coders/editblock_prompts.py
aider/coders/editor_editblock_coder.py
aider/coders/editor_editblock_prompts.py
aider/coders/editor_whole_coder.py
aider/coders/editor_whole_prompts.py
aider/coders/help_coder.py
aider/coders/help_prompts.py
aider/coders/large_context_retriever.py
aider/coders/large_context_retriever_prompts.py
aider/coders/search_replace.py
aider/coders/single_wholefile_func_coder.py
aider/coders/single_wholefile_func_prompts.py
aider/coders/udiff_coder.py
aider/coders/udiff_prompts.py
aider/coders/wholefile_coder.py
aider/coders/wholefile_func_coder.py
aider/coders/wholefile_func_prompts.py
aider/coders/wholefile_prompts.py
aider/operator/__init__.py
aider/operator/core.py
aider/queries/tree-sitter-language-pack/README.md
aider/queries/tree-sitter-language-pack/arduino-tags.scm
vnow_aider_chat-0.8.0.dist-info/licenses/LICENSE.txt
vnow_aider_chat-0.8.0.dist-info/METADATA
vnow_aider_chat-0.8.0.dist-info/WHEEL
vnow_aider_chat-0.8.0.dist-info/entry_points.txt
vnow_aider_chat-0.8.0.dist-info/top_level.txt
vnow_aider_chat-0.8.0.dist-info/RECORD
